mseedlib-0.0.10.dist-info/RECORD
mseedlib-0.0.10.dist-info/METADATA
mseedlib-0.0.10.dist-info/WHEEL
mseedlib-0.0.10.dist-info/licenses/LICENSE
mseedlib/exceptions.py
mseedlib/__version__.py
mseedlib/msrecord.py
mseedlib/libmseed.h
mseedlib/clib.py
mseedlib/util.py
mseedlib/msrecord_buffer_reader.py
mseedlib/definitions.py
mseedlib/msrecord_reader.py
mseedlib/mstracelist.py
mseedlib/libmseed.so
mseedlib/__init__.py
