Metadata-Version: 2.4
Name: mseedlib
Version: 0.0.10
Summary: ⚠️ DEPRECATED: This project is no longer maintained, use pymseed instead
Project-URL: Homepage, https://github.com/EarthScope/mseedlib
Author-email: EarthScope Data Services <software@earthscope.org>
License: Apache-2.0
License-File: LICENSE
Keywords: data,deprecated,miniseed,mseed,seismic,seismology,waveform
Classifier: Development Status :: 7 - Inactive
Classifier: Intended Audience :: Science/Research
Classifier: License :: OSI Approved :: Apache Software License
Classifier: Operating System :: MacOS :: MacOS X
Classifier: Operating System :: Microsoft :: Windows
Classifier: Operating System :: POSIX :: Linux
Classifier: Operating System :: POSIX :: Other
Classifier: Programming Language :: Python :: 3
Classifier: Programming Language :: Python :: 3.9
Classifier: Programming Language :: Python :: 3.10
Classifier: Programming Language :: Python :: 3.11
Classifier: Programming Language :: Python :: 3.12
Classifier: Programming Language :: Python :: 3.13
Classifier: Programming Language :: Python :: Implementation :: CPython
Classifier: Topic :: Scientific/Engineering
Requires-Python: >=3.9
Provides-Extra: dev
Requires-Dist: black==25.1.0; extra == 'dev'
Requires-Dist: pytest==8.3.4; extra == 'dev'
Provides-Extra: numpy
Requires-Dist: numpy==2.0.2; extra == 'numpy'
